Workbook

Sheet Instructions
C7: Last updated: 22 October 2014. Check for the latest version.

Sheet Results
C11: Summary of results
D13: Raw score | E13: # Questions | F13: # Answers | G13: Score
C14: Home Page | D14: =SUM('Home Page'!D10:D29) -> 0 | E14: =COUNTA('Home Page'!C10:C29) -> 20 | F14: =COUNT('Home Page'!D10:D29) -> 0 | G14: =IF(F14=0,"",(D14+F14)/(2*F14))
C15: Task Orientation | D15: =SUM('Task Orientation'!D10:D53) -> 0 | E15: =COUNTA('Task Orientation'!C10:C53) -> 44 | F15: =COUNT('Task Orientation'!D10:D53) -> 0 | G15: =IF(F15=0,"",(D15+F15)/(2*F15))
C16: Navigation & IA | D16: =SUM('Navigation & IA'!D10:D38) -> 0 | E16: =COUNTA('Navigation & IA'!C10:C38) -> 29 | F16: =COUNT('Navigation & IA'!D10:D38) -> 0 | G16: =IF(F16=0,"",(D16+F16)/(2*F16))
C17: Forms & Data Entry | D17: =SUM('Forms & Data Entry'!D10:D32) -> 0 | E17: =COUNTA('Forms & Data Entry'!C10:C32) -> 23 | F17: =COUNT('Forms & Data Entry'!D10:D32) -> 0 | G17: =IF(F17=0,"",(D17+F17)/(2*F17))
C18: Trust & Credibility | D18: =SUM('Trust & Credibility'!D10:D22) -> 0 | E18: =COUNTA('Trust & Credibility'!C10:C22) -> 13 | F18: =COUNT('Trust & Credibility'!D10:D22) -> 0 | G18: =IF(F18=0,"",(D18+F18)/(2*F18))
C19: Writing & Content Quality | D19: =SUM('Writing & Content Quality'!D10:D32) -> 0 | E19: =COUNTA('Writing & Content Quality'!C10:C32) -> 23 | F19: =COUNT('Writing & Content Quality'!D10:D32) -> 0 | G19: =IF(F19=0,"",(D19+F19)/(2*F19))
C20: Page Layout & Visual Design | D20: =SUM('Page Layout & Visual Design'!D10:D47) -> 0 | E20: =COUNTA('Page Layout & Visual Design'!C10:C47) -> 38 | F20: =COUNT('Page Layout & Visual Design'!D10:D47) -> 0 | G20: =IF(F20=0,"",(D20+F20)/(2*F20))
C21: Search | D21: =SUM(Search!D10:D29) -> 0 | E21: =COUNTA(Search!C10:C29) -> 20 | F21: =COUNT(Search!D10:D29) -> 0 | G21: =IF(F21=0,"",(D21+F21)/(2*F21))
C22: Help, Feedback & Error Tolerance | D22: =SUM('Help, Feedback, Error Tolerance'!D10:D46) -> 0 | E22: =COUNTA('Help, Feedback, Error Tolerance'!C10:C46) -> 37 | F22: =COUNT('Help, Feedback, Error Tolerance'!D10:D46) -> 0 | G22: =IF(F22=0,"",(D22+F22)/(2*F22))
C23: Overall score | E23: =SUM(E14:E22) -> 247 | F23: =SUM(F14:F22) -> 0 | G23: =IF(G14="","",AVERAGE(G14:G22))

Sheet Home Page
C8: Checkpoint | I8: Comments
C10: The items on the home page are clearly focused on users’ key tasks (“featuritis” has been avoided)
C11: The home page contains a search input box
C12: Product categories are provided and clearly visible on the homepage
C13: Useful content is presented on the home page or within one click of the home page
C14: The home page shows good examples of real site content
C15: Links on the home page begin with the most important keyword (e.g. "Sun holidays" not "Holidays in the sun")
C16: There is a short list of items recently featured on the homepage, supplemented with a link to archival content
C17: Navigation areas on the home page are not over-formatted and users will not mistake them for adverts
C18: The value proposition is clearly stated on the home page (e.g. with a tagline or welcome blurb)
C19: The home page contains meaningful graphics, not clip art or pictures of models
C20: Navigation choices are ordered in the most logical or task-oriented manner (with the less important corporate information at the bottom)
C21: The title of the home page will provide good visibility in search engines like Google
... C29: The home page looks like a home page; pages lower in the site will not be confused with it

Sheet Task Orientation
C8: Checkpoint | I8: Comments
C10: The site is free from irrelevant, unnecessary and distracting information
C11: Excessive use of scripts, applets, movies, audio files, graphics and images has been avoided
C12: The site avoids unnecessary registration
C13: The critical path (e.g. purchase, subscription) is clear, with no distractions on route
C14: Information is presented in a simple, natural and logical order
C15: The number of screens required per task has been minimised
C16: The site requires minimal scrolling and clicking
C17: The site correctly anticipates and prompts for the user’s probable next activity
C18: When graphs are shown, users have access to the actual data (e.g. numeric annotation on bar charts)
C19: Activities allocated to the user or the computer take full advantage of the strengths of each (look for actions that can be done automatically by the site, e.g. postcode lookup)
C20: Users can complete common tasks quickly
C21: Items can be compared easily when this is necessary for the task (e.g. product comparisons)
... C53: The site allows the user to customise operational time parameters (e.g. time until automatic logout)

Sheet Navigation & IA
C8: Checkpoint | I8: Comments
C10: There is a convenient and obvious way to move between related pages and sections and it is easy to return to the home page
C11: The information that users are most likely to need is easy to navigate to from most pages
C12: Navigation choices are ordered in the most logical or task-oriented manner
C13: The navigation system is broad and shallow (many items on a menu) rather than deep (many menu levels)
C14: The site structure is simple, with a clear conceptual model and no unnecessary levels
C15: The major sections of the site are available from every page (persistent navigation) and there are no dead ends
C16: Navigation tabs are located at the top of the page, and look like clickable versions of real-world tabs
C17: There is a site map that provides an overview of the site's content
C18: The site map is linked to from every page
C19: The site map provides a concise overview of the site, not a rehash of the main navigation or a list of every single topic
C20: Good navigational feedback is provided (e.g. showing where you are in the site)
C21: Category labels accurately describe the information in the category
... C38: Menu instructions, prompts and messages appear on the same place on each screen

Sheet Forms & Data Entry
C8: Checkpoint | I8: Comments
C10: Fields in data entry screens contain default values when appropriate and show the structure of the data and the field length
C11: When a task involves source documents (such as a paper form), the interface is compatible with the characteristics of the source document
C12: The site automatically enters field formatting data (e.g. currency symbols, commas for 1000s, trailing or leading spaces). Users do not need to enter characters like £ or %.
C13: Field labels on forms clearly explain what entries are desired
C14: Text boxes on forms are the right length for the expected answer
C15: There is a clear distinction between “required” and “optional” fields on forms
C16: The same form is used for both logging in and registering (i.e. it's like Amazon)
C17: Forms pre-warn the user if external information is needed for completion (e.g. a passport number)
C18: Questions on forms are grouped logically, and each group has a heading
C19: Fields on forms contain hints, examples or model answers to demonstrate the expected input
C20: When field labels on forms take the form of questions, the questions are stated in clear, simple language
C21: Pull-down menus, radio buttons and check boxes are used in preference to text entry fields on forms (i.e. text entry fields are not overused)
... C32: Labels are close to the data entry fields (e.g. labels are right justified)

Sheet Trust & Credibility
C8: Checkpoint | I8: Comments
C10: The content is up-to-date, authoritative and trustworthy
C11: The site contains third-party support (e.g. citations, testimonials) to verify the accuracy of information.
C12: It is clear that there is a real organisation behind the site (e.g. there is a physical address or a photo of the office)
C13: The company comprises acknowledged experts (look for credentials)
C14: The site avoids advertisements, especially pop-ups.
C15: Delivery costs are highlighted at the very beginning of checkout
C16: The site avoids marketing waffle
C17: Each page is clearly branded so that the user knows he is still in the same site
C18: It is easy to contact someone for assistance and a reply is received quickly
C19: The content is fresh: it is updated frequently and the site includes recent content
C20: The site is free of typographic errors and spelling mistakes
C21: The visual design complements the brand and any offline marketing messages
C22: There are real people behind the organisation and they are honest and trustworthy (look for bios)

Sheet Writing & Content Quality
C8: Checkpoint | I8: Comments
C10: The site has compelling and unique content
C11: Text is concise, with no needless instructions or welcome notes
C12: Each content page begins with conclsuions or implications and the text is written with an inverted pyramid style
C13: Pages use bulleted and numbered lists in preference to narrative text
C14: Lists are prefaced with a concise introduction (e.g. a word or phrase), helping users appreciate how the items are related to one another
C15: The most important items in a list are placed at the top
C16: Information is organised hierarchically, from the general to the specific, and the organisation is clear and logical
C17: Content has been specifically created for the web (web pages do not comprise repurposed material from print publications such as brochures)
C18: Product pages contain the detail necessary to make a purchase, and users can zoom in on product images
C19: Hypertext has been appropriately used to structure content
C20: Sentences are written in the active voice
C21: Pages are quick to scan, with ample headings and sub-headings and short paragraphs
... C32: Text links are long enough to be understood, but short enough to minimise wrapping (especially when used as a navigation list)

Sheet Page Layout & Visual Design
C8: Checkpoint | I8: Comments
C10: The screen density is appropriate for the target users and their tasks
C11: The layout helps focus attention on what to do next
C12: On all pages, the most important information (such as frequently used topics, features and functions) is presented on the first screenful of information (“above the fold”)
C13: The site can be used without scrolling horizontally
C14: Things that are clickable (like buttons) are obviously pressable
C15: Items that aren't clickable do not have characteristics that suggest that they are
C16: The functionality of buttons and controls is obvious from their labels or from their design
C17: Clickable images include redundant text labels (i.e. there is no 'mystery meat' navigation)
C18: Hypertext links are easy to identify without needing to 'minesweep' (e.g. underlined)
C19: Fonts are used consistently
C20: The relationship between controls and their actions is obvious
C21: Icons and graphics are standard and/or intuitive (concrete and familiar)
... C47: Related information and functions are clustered together, and each group can be scanned in a single fixation (5-deg, about 4.4cm diam circle on screen)

Sheet Search
C8: Checkpoint | I8: Comments
C10: The default search is intuitive to configure (no Boolean operators)
C11: The search results page shows the user what was searched for and it is easy to edit and resubmit the search
C12: Search results are clear, useful and ranked by relevance
C13: The search results page makes it clear how many results were retrieved, and the number of results per page can be configured by the user
C14: If no results are returned, the system offers ideas or options for improving the query based on identifiable problems with the user's input
C15: The search engine handles empty queries gracefully
C16: The most common queries (as reflected in the site log) produce useful results
C17: The search engine includes templates, examples or hints on how to use it effectively
C18: The site includes a more powerful search interface available to help users refine their searches (preferably named "revise search" or "refine search", not "advanced search)
C19: The search results page does not show duplicate results (either perceived duplicates or actual duplicates)
C20: The search box is long enough to handle common query lengths
C21: Searches cover the entire web site, not a portion of it
... C29: The search engine provides an option for similarity search (“more like this”)

Sheet Help, Feedback, Error Tolerance
C8: Checkpoint | I8: Comments
C10: The FAQ or on-line help provides step-by-step instructions to help users carry out the most important tasks
C11: It is easy to get help in the right form and at the right time
C12: Prompts are brief and unambiguous
C13: The user does not need to consult user manuals or other external information to use the site
C14: The site uses a customised 404 page, which includes tips on how to find the missing page and links to “Home” and Search
C15: The site provides good feedback (e.g. progress indicators or messages) when needed (e.g. during checkout)
C16: Users are given help in choosing products
C17: User confirmation is required before carrying out potentially “dangerous” actions (e.g. deleting something)
C18: Confirmation pages are clear
C19: Error messages contain clear instructions on what to do next
C20: Immediately prior to commiting to the purchase, the site shows the user a clear summary page and this will not be confused with a purchase confirmation page
C21: When the user needs to choose between different options (such as in a dialog box), the options are obvious
... C46: It is easy to “undo” (or “cancel”) and “redo” actions

Sheet Further reading
